{"code":"ER","states":[{"name":"Anseba Region","state_code":"AN","latitude":"16.47455310","longitude":"37.80876930","cities":[{"name":"Keren","latitude":"15.77792000","longitude":"38.45107000"}]},{"name":"Debub Region","state_code":"DU","latitude":"14.94786920","longitude":"39.15436770","cities":[{"name":"Adi Keyh","latitude":"14.84444000","longitude":"39.37722000"},{"name":"Dek’emhāre","latitude":"15.07000000","longitude":"39.04750000"},{"name":"Mendefera","latitude":"14.88722000","longitude":"38.81528000"}]},{"name":"Gash-Barka Region","state_code":"GB","latitude":"15.40688250","longitude":"37.63866220","cities":[{"name":"Ak’ordat","latitude":"15.54798000","longitude":"37.88291000"},{"name":"Barentu","latitude":"15.10582000","longitude":"37.59067000"},{"name":"Teseney","latitude":"15.11000000","longitude":"36.65750000"}]},{"name":"Maekel Region","state_code":"MA","latitude":"15.35514090","longitude":"38.86236830","cities":[{"name":"Asmara","latitude":"15.33805000","longitude":"38.93184000"}]},{"name":"Northern Red Sea Region","state_code":"SK","latitude":"16.25839970","longitude":"38.82054540","cities":[{"name":"Massawa","latitude":"15.60811000","longitude":"39.47455000"}]},{"name":"Southern Red Sea Region","state_code":"DK","latitude":"13.51371030","longitude":"41.76064720","cities":[{"name":"Assab","latitude":"13.00917000","longitude":"42.73944000"},{"name":"Edd","latitude":"13.93088000","longitude":"41.69380000"}]}]}