{"code":"MV","states":[{"name":"Addu Atoll","state_code":"01","latitude":"-0.63009950","longitude":"73.15856260","cities":[{"name":"Hithadhoo","latitude":"-0.60000000","longitude":"73.08333000"},{"name":"Meedhoo","latitude":"-0.58333000","longitude":"73.23333000"}]},{"name":"Alif Alif Atoll","state_code":"02","latitude":"4.08500000","longitude":"72.85154790","cities":[]},{"name":"Alif Dhaal Atoll","state_code":"00","latitude":"3.65433020","longitude":"72.80427970","cities":[]},{"name":"Central Province","state_code":"CE","latitude":null,"longitude":null,"cities":[]},{"name":"Dhaalu Atoll","state_code":"17","latitude":"2.84685020","longitude":"72.94605660","cities":[{"name":"Kudahuvadhoo","latitude":"2.67075000","longitude":"72.89437000"}]},{"name":"Faafu Atoll","state_code":"14","latitude":"3.23094090","longitude":"72.94605660","cities":[]},{"name":"Gaafu Alif Atoll","state_code":"27","latitude":"0.61248130","longitude":"73.32370800","cities":[{"name":"Viligili","latitude":"0.75906000","longitude":"73.43296000"}]},{"name":"Gaafu Dhaalu Atoll","state_code":"28","latitude":"0.35880400","longitude":"73.18216230","cities":[{"name":"Thinadhoo","latitude":"0.53060000","longitude":"72.99969000"}]},{"name":"Gnaviyani Atoll","state_code":"29","latitude":"-0.30064250","longitude":"73.42391430","cities":[{"name":"Fuvahmulah","latitude":"-0.29878000","longitude":"73.42403000"}]},{"name":"Haa Alif Atoll","state_code":"07","latitude":"6.99034880","longitude":"72.94605660","cities":[{"name":"Dhidhdhoo","latitude":"6.88744000","longitude":"73.11402000"}]},{"name":"Haa Dhaalu Atoll","state_code":"23","latitude":"6.57827170","longitude":"72.94605660","cities":[{"name":"Kulhudhuffushi","latitude":"6.62207000","longitude":"73.06998000"}]},{"name":"Kaafu Atoll","state_code":"26","latitude":"4.45589790","longitude":"73.55941280","cities":[{"name":"Guraidhoo","latitude":"3.90045000","longitude":"73.46623000"},{"name":"Hulhumale","latitude":"4.21169000","longitude":"73.54008000"},{"name":"Maafushi","latitude":"3.94231000","longitude":"73.49070000"},{"name":"Male","latitude":"4.17521000","longitude":"73.50916000"}]},{"name":"Laamu Atoll","state_code":"05","latitude":"1.94307370","longitude":"73.41802110","cities":[{"name":"Fonadhoo","latitude":"1.83243000","longitude":"73.50257000"}]},{"name":"Lhaviyani Atoll","state_code":"03","latitude":"5.37470210","longitude":"73.51229280","cities":[{"name":"Naifaru","latitude":"5.44438000","longitude":"73.36571000"}]},{"name":"Malé","state_code":"MLE","latitude":"46.34888670","longitude":"10.90724890","cities":[]},{"name":"Meemu Atoll","state_code":"12","latitude":"3.00903450","longitude":"73.51229280","cities":[{"name":"Muli","latitude":"2.91667000","longitude":"73.56667000"}]},{"name":"Noonu Atoll","state_code":"25","latitude":"5.85512760","longitude":"73.32370800","cities":[{"name":"Manadhoo","latitude":"5.76687000","longitude":"73.41360000"}]},{"name":"North Central Province","state_code":"NC","latitude":null,"longitude":null,"cities":[]},{"name":"North Province","state_code":"NO","latitude":"8.88550270","longitude":"80.27673270","cities":[]},{"name":"Raa Atoll","state_code":"13","latitude":"5.60064570","longitude":"72.94605660","cities":[{"name":"Ugoofaaru","latitude":"5.66812000","longitude":"73.03017000"}]},{"name":"Shaviyani Atoll","state_code":"24","latitude":"6.17511000","longitude":"73.13496050","cities":[{"name":"Funadhoo","latitude":"6.15091000","longitude":"73.29013000"}]},{"name":"South Central Province","state_code":"SC","latitude":"7.25649960","longitude":"80.72144170","cities":[{"name":"Mahibadhoo","latitude":"3.75713000","longitude":"72.96893000"}]},{"name":"South Province","state_code":"SU","latitude":"-21.74820060","longitude":"166.17837390","cities":[]},{"name":"Thaa Atoll","state_code":"08","latitude":"2.43111610","longitude":"73.18216230","cities":[{"name":"Veymandoo","latitude":"2.18772000","longitude":"73.09556000"}]},{"name":"Upper South Province","state_code":"US","latitude":"0.23070000","longitude":"73.27948460","cities":[]},{"name":"Vaavu Atoll","state_code":"04","latitude":"3.39554380","longitude":"73.51229280","cities":[{"name":"Felidhoo","latitude":"3.47182000","longitude":"73.54699000"}]}]}